setup.py
py_sam.egg-info/PKG-INFO
py_sam.egg-info/SOURCES.txt
py_sam.egg-info/dependency_links.txt
py_sam.egg-info/requires.txt
py_sam.egg-info/top_level.txt
sam/13scene_experiment.py
sam/8scene_experiment.py
sam/__init__.py
sam/arff.py
sam/cv.py
sam/evidence_to_sam_corpus.py
sam/experiment_utils.py
sam/make_gist_arff.py
sam/make_gist_corpus.py
sam/math_util.py
sam/optimize.py
sam/pickle_file_io.py
sam/profile_util.py
sam/test.py
sam/condor/__init__.py
sam/condor/condorizable.py
sam/corpus/__init__.py
sam/corpus/corpus.py
sam/corpus/evidence.py
sam/corpus/labelers.py
sam/vem/__init__.py
sam/vem/__main__.py
sam/vem/cli.py
sam/vem/model.py
sam/vem/svm/__init__.py
sam/vem/svm/dataset.py
sam/vem/svm/loss.py
sam/vem/svm/topic_svm.py
sam/vision/__init__.py
sam/vision/gist.py
weka/__init__.py
weka/cross_validator_cli.py