Metadata-Version: 1.0
Name: py-sam
Version: 0.1
Summary: the spherical admixture topic model
Home-page: http://www.cs.utexas.edu/~austin/
Author: Austin Waters
Author-email: austin@cs.utexas.edu
License: MIT
Keywords: topic models machine learning
Platform: UNKNOWN
Classifier: Development Status :: 4 - Beta
Classifier: Programming Language :: Python :: 2.6
Classifier: Operating System :: Unix
Classifier: Topic :: Utilities
Classifier: Topic :: Software Development :: Libraries
Classifier: Topic :: Scientific/Engineering :: Artificial Intelligence
